{
	"version": 1,
	"collections": [
		{
			"id": "6bcd723a-0e94-db05-7e28-6171e743cb98",
			"name": "q3",
			"description": "",
			"order": [
				"d8b2cacf-477d-e9b8-d712-9a74a3b52527",
				"172c8912-3d22-9fae-f51f-213ed0f66c38",
				"ec67471c-d463-f916-3a65-1bb67919c9da",
				"a2285805-dec4-6c7a-b690-1593b1c00e14",
				"d6bd4e63-298f-f697-21d4-ab640b58062a",
				"be0d9c5f-ccfc-729a-eef8-cd353b3eb841",
				"9716139e-af1b-3768-7f1b-1a98124ce89c",
				"5f4cacb5-7a2f-9069-3dea-23886501685e",
				"6f61ef05-6fe6-cc19-1ca7-71a9699ef59d",
				"13fef681-70ba-d1b8-5ebe-19b4d1667415",
				"73c615ec-0a56-c76b-8535-13a70ce27a3b",
				"afccd0a9-9536-2a17-66bf-b22f348e6571",
				"fa5352cf-97d3-3635-bc84-31aaa1ee064c",
				"46766ef1-e044-0761-0832-7597434d4067",
				"b38889aa-5a5b-97f9-3e18-2b8d0aadf027"
			],
			"folders": [],
			"timestamp": 1472340134304,
			"synced": false,
			"remote_id": 0,
			"owner": "347292",
			"sharedWithTeam": false,
			"subscribed": false,
			"remoteLink": "",
			"remoteLinkUpdatedAt": null,
			"public": false,
			"createdAt": 1472340134304,
			"updatedAt": 1474064366635,
			"write": true,
			"published": false,
			"favorite": true,
			"permissions": {},
			"syncedPermissions": {},
			"requests": [
				{
					"id": "13fef681-70ba-d1b8-5ebe-19b4d1667415",
					"headers": "Content-Type: application/json\n",
					"url": "http://127.0.0.1:2080/user",
					"preRequestScript": null,
					"pathVariables": {},
					"method": "POST",
					"data": "{ \"name\": \"tom\",\n\"email\": \"tom@test.com\"\n}",
					"dataMode": "raw",
					"version": 2,
					"tests": null,
					"currentHelper": "normal",
					"helperAttributes": {},
					"time": 1473132917714,
					"name": "add user",
					"description": "",
					"collectionId": "6bcd723a-0e94-db05-7e28-6171e743cb98",
					"responses": []
				},
				{
					"id": "172c8912-3d22-9fae-f51f-213ed0f66c38",
					"headers": "",
					"url": "http://{{blob_host}}/api/v1/blobs/{{team}}",
					"preRequestScript": null,
					"pathVariables": {},
					"method": "GET",
					"data": null,
					"dataMode": "params",
					"version": 2,
					"tests": null,
					"currentHelper": "normal",
					"helperAttributes": {},
					"time": 1474056479284,
					"name": "get blob",
					"description": "",
					"collectionId": "6bcd723a-0e94-db05-7e28-6171e743cb98",
					"responses": []
				},
				{
					"id": "46766ef1-e044-0761-0832-7597434d4067",
					"headers": "Content-Type: application/json\n",
					"url": "http://{{host}}:8082/api/servers/",
					"pathVariables": {},
					"preRequestScript": null,
					"method": "GET",
					"collectionId": "6bcd723a-0e94-db05-7e28-6171e743cb98",
					"data": "{ \"name\": \"server9\",\n\"description\": \"from rest\"\n}",
					"dataMode": "raw",
					"name": "get servers",
					"description": "",
					"descriptionFormat": "html",
					"time": 1474057038787,
					"version": 2,
					"responses": [],
					"tests": null,
					"currentHelper": "normal",
					"helperAttributes": {}
				},
				{
					"id": "5f4cacb5-7a2f-9069-3dea-23886501685e",
					"headers": "Content-Type: application/json\n",
					"url": "http://{{host}}:{{labserver_port}}/items",
					"preRequestScript": null,
					"pathVariables": {},
					"method": "GET",
					"data": "{ \"name\": \"server9\",\n\"description\": \"from rest\"\n}",
					"dataMode": "raw",
					"version": 2,
					"tests": null,
					"currentHelper": "normal",
					"helperAttributes": {},
					"time": 1474056723986,
					"name": "get items",
					"description": "",
					"collectionId": "6bcd723a-0e94-db05-7e28-6171e743cb98",
					"responses": []
				},
				{
					"id": "6f61ef05-6fe6-cc19-1ca7-71a9699ef59d",
					"headers": "Content-Type: application/json\n",
					"url": "http://127.0.0.1:2080/users",
					"preRequestScript": null,
					"pathVariables": {},
					"method": "GET",
					"data": "{ \"name\": \"server9\",\n\"description\": \"from rest\"\n}",
					"dataMode": "raw",
					"version": 2,
					"tests": null,
					"currentHelper": "normal",
					"helperAttributes": {},
					"time": 1473132853031,
					"name": "get users",
					"description": "",
					"collectionId": "6bcd723a-0e94-db05-7e28-6171e743cb98",
					"responses": []
				},
				{
					"id": "73c615ec-0a56-c76b-8535-13a70ce27a3b",
					"headers": "Content-Type: application/json\n",
					"url": "http://{{host}}:{{labserver_port}}/item/server9",
					"preRequestScript": null,
					"pathVariables": {},
					"method": "GET",
					"data": "{ \"name\": \"server9\",\n\"description\": \"from rest\"\n}",
					"dataMode": "raw",
					"version": 2,
					"tests": null,
					"currentHelper": "normal",
					"helperAttributes": {},
					"time": 1474056701136,
					"name": "get item",
					"description": "",
					"collectionId": "6bcd723a-0e94-db05-7e28-6171e743cb98",
					"responses": []
				},
				{
					"id": "9716139e-af1b-3768-7f1b-1a98124ce89c",
					"headers": "Content-Type: application/json\n",
					"url": "http://{{host}}:{{labserver_port}}/item",
					"preRequestScript": null,
					"pathVariables": {},
					"method": "POST",
					"data": "{ \"name\": \"server9\",\n\"description\": \"from rest\"\n}",
					"dataMode": "raw",
					"version": 2,
					"tests": null,
					"currentHelper": "normal",
					"helperAttributes": {},
					"time": 1474056409084,
					"name": "add item",
					"description": "",
					"collectionId": "6bcd723a-0e94-db05-7e28-6171e743cb98",
					"responses": []
				},
				{
					"id": "a2285805-dec4-6c7a-b690-1593b1c00e14",
					"headers": "",
					"url": "http://{{host}}:{{journal_port}}/api/topics",
					"preRequestScript": null,
					"pathVariables": {},
					"method": "GET",
					"data": null,
					"dataMode": "params",
					"version": 2,
					"tests": null,
					"currentHelper": "normal",
					"helperAttributes": {},
					"time": 1474056253876,
					"name": "get topics",
					"description": "",
					"collectionId": "6bcd723a-0e94-db05-7e28-6171e743cb98",
					"responses": []
				},
				{
					"id": "afccd0a9-9536-2a17-66bf-b22f348e6571",
					"headers": "Content-Type: application/json\n",
					"url": "http://{{host}}:8082/item/server1/reservation",
					"preRequestScript": null,
					"pathVariables": {},
					"method": "POST",
					"data": "{ \"username\": \"tom\",\n\"begin\": \"2016-09-06T00:09:04.032-04:00\",\n\"hoursheld\": 3\n}",
					"dataMode": "raw",
					"version": 2,
					"tests": null,
					"currentHelper": "normal",
					"helperAttributes": {},
					"time": 1474056797145,
					"name": "post reservation",
					"description": "",
					"collectionId": "6bcd723a-0e94-db05-7e28-6171e743cb98",
					"responses": []
				},
				{
					"id": "b38889aa-5a5b-97f9-3e18-2b8d0aadf027",
					"headers": "Content-Type: application/json\n",
					"url": "http://{{host}}:8082/api/reservations/",
					"pathVariables": {},
					"preRequestScript": null,
					"method": "POST",
					"collectionId": "6bcd723a-0e94-db05-7e28-6171e743cb98",
					"data": "\n{\n  \"name\": \"testres-servername1\",\n  \"start_date\": \"2016-01-01T06:00:00.000Z\",\n  \"end_date\": \"2099-12-31T00:00:00.000Z\",\n  \"server_name\": \"servername1\"\n}",
					"dataMode": "raw",
					"name": "post reservation",
					"description": "",
					"descriptionFormat": "html",
					"time": 1474064366609,
					"version": 2,
					"responses": [],
					"tests": null,
					"currentHelper": "normal",
					"helperAttributes": {}
				},
				{
					"id": "be0d9c5f-ccfc-729a-eef8-cd353b3eb841",
					"headers": "Content-Type: application/json\n",
					"url": "http://192.168.4.84:8080/api/topic/a",
					"preRequestScript": null,
					"pathVariables": {},
					"method": "GET",
					"data": "{\n    \"id\": 0,\n    \"message\": \"message text\"\n}",
					"dataMode": "raw",
					"tests": null,
					"currentHelper": "normal",
					"helperAttributes": {},
					"time": 1472342054230,
					"name": "get topic item",
					"description": "",
					"collectionId": "6bcd723a-0e94-db05-7e28-6171e743cb98",
					"responses": []
				},
				{
					"id": "d6bd4e63-298f-f697-21d4-ab640b58062a",
					"headers": "Content-Type: application/json\n",
					"url": "http://{{host}}:{{journal_port}}/api/topic/10",
					"preRequestScript": null,
					"pathVariables": {},
					"method": "POST",
					"data": "{ \n    \"id\": 0,\n    \"message\": \"\"\n}",
					"dataMode": "raw",
					"tests": null,
					"currentHelper": "normal",
					"helperAttributes": {},
					"time": 1474056331694,
					"name": "post topic",
					"description": "",
					"collectionId": "6bcd723a-0e94-db05-7e28-6171e743cb98",
					"responses": []
				},
				{
					"id": "d8b2cacf-477d-e9b8-d712-9a74a3b52527",
					"headers": "Content-Type: application/json\n",
					"url": "http://{{blob_host}}/api/v1/blobs",
					"preRequestScript": null,
					"pathVariables": {},
					"method": "POST",
					"data": "{\n  \"id\": {{team}},\n  \"name\": \"\",\n  \"version\": \"\",\n  \"content\": \"\"\n}",
					"dataMode": "raw",
					"version": 2,
					"tests": null,
					"currentHelper": "normal",
					"helperAttributes": {},
					"time": 1474056508321,
					"name": "post a blob",
					"description": "",
					"collectionId": "6bcd723a-0e94-db05-7e28-6171e743cb98",
					"responses": []
				},
				{
					"id": "ec67471c-d463-f916-3a65-1bb67919c9da",
					"headers": "",
					"url": "http://{{blob_host}}/api/v1/blobs/{{team}}",
					"preRequestScript": null,
					"pathVariables": {},
					"method": "DELETE",
					"data": null,
					"dataMode": "params",
					"version": 2,
					"tests": null,
					"currentHelper": "normal",
					"helperAttributes": {},
					"time": 1474056540654,
					"name": "delete blob",
					"description": "",
					"collectionId": "6bcd723a-0e94-db05-7e28-6171e743cb98",
					"responses": []
				},
				{
					"id": "fa5352cf-97d3-3635-bc84-31aaa1ee064c",
					"headers": "Content-Type: application/json\n",
					"url": "http://{{host}}:8082/api/reservations/",
					"preRequestScript": null,
					"pathVariables": {},
					"method": "GET",
					"data": "{ \"name\": \"server9\",\n\"description\": \"from rest\"\n}",
					"dataMode": "raw",
					"version": 2,
					"tests": null,
					"currentHelper": "normal",
					"helperAttributes": {},
					"time": 1474057012123,
					"name": "get reservations",
					"description": "",
					"collectionId": "6bcd723a-0e94-db05-7e28-6171e743cb98",
					"responses": []
				}
			]
		}
	],
	"environments": [

		{
			"id": "3db97b85-ec5d-a4b3-60b6-c4f22f379bb3",
			"name": "q3-docker-sandbox",
			"values": [
				{
					"key": "host",
					"value": "q3.butterhead.net",
					"type": "text",
					"enabled": true
				},
				{
					"key": "team",
					"value": "10",
					"type": "text",
					"enabled": true
				},
				{
					"key": "journal_port",
					"value": "8080",
					"type": "text",
					"enabled": true
				},
				{
					"key": "approval_host",
					"value": "approval.vmwaredevops.appspot.com",
					"type": "text",
					"enabled": true
				},
				{
					"key": "labserver_port",
					"value": "2080",
					"type": "text",
					"enabled": true
				},
				{
					"key": "exception_port",
					"value": "8081",
					"type": "text",
					"enabled": true
				},
				{
					"key": "reservation_port",
					"value": "8082",
					"type": "text",
					"enabled": true
				},
				{
					"key": "updater_port",
					"value": "8083",
					"type": "text",
					"enabled": true
				},
				{
					"key": "blob_host",
					"value": "blobs.vmwaredevops.appspot.com",
					"type": "text",
					"enabled": true
				}
			],
			"team": null,
			"timestamp": 1474063713621
		},
		{
			"id": "4809abf4-aea9-71ec-ab75-c99dbea126a5",
			"name": "dev packerd",
			"values": [
				{
					"key": "port",
					"value": "64154",
					"type": "text",
					"enabled": true,
					"hovered": false
				},
				{
					"key": "host",
					"value": "127.0.0.1",
					"type": "text",
					"enabled": true,
					"hovered": false
				},
				{
					"key": "scheme",
					"value": "https",
					"type": "text",
					"enabled": true,
					"hovered": false
				},
				{
					"key": "tlsport",
					"value": "64155",
					"type": "text",
					"enabled": true,
					"hovered": false
				}
			],
			"team": null,
			"timestamp": 1474063713641
		}

	],
	"headerPresets": [],
	"globals": []
}